crilot/__init__.py
crilot/main.py
crilot/utils.py
crilot-5.1.dist-info/METADATA
crilot-5.1.dist-info/WHEEL
crilot-5.1.dist-info/top_level.txt
crilot-5.1.dist-info/RECORD
