Metadata-Version: 2.2
Name: crilot
Version: 5.1
Summary: Krill ⬌ Lotin matnlarini oson konvertatsiya qilish uchun Python kutubxonasi!
Home-page: https://github.com/axmadjonqaxxorovc/
Author: Axmadjon Qaxxorov
Project-URL: 🌐 Taplink, https://taplink.cc/qaxxorovc
Project-URL: 📺 YouTube, https://youtube.com/@axmadjonqaxxorovc
Project-URL: ✈️ Telegram, https://t.me/axmadjonqaxxorovc
Classifier: Development Status :: 4 - Beta
Classifier: Programming Language :: Python :: 3
Classifier: License :: OSI Approved :: MIT License
Classifier: Operating System :: OS Independent
Requires-Python: >=3.6
Dynamic: author
Dynamic: classifier
Dynamic: description
Dynamic: description-content-type
Dynamic: home-page
Dynamic: project-url
Dynamic: requires-python
Dynamic: summary
